modules/c64/pla.v
module pla (
           input[15:0] A,
           input _CHAREN,  _HIRAM,  _LORAM,
           input _CAS,
           input VA12, VA13, _VA14,
           input _AEC,  BA,
           input _GAME,  _EXROM,  R__W,
           output ROMH ,ROML, GR_W , CHAROM, KERNAL , BASIC , CASRAM,
           output CIA1,CIA2,SID,VIC,COLOR_RAM,IO1,IO2
       );

wire I_O;
wire A8 = A[8];
wire A9 = A[9];
wire A10 = A[10];
wire A11 = A[11];
wire A12 = A[12];
wire A13 = A[13];
wire A14 = A[14];
wire A15 = A[15];

assign VIC = I_O && !A11 && !A10;
assign SID = I_O && !A11 &&  A10;
assign COLOR_RAM = I_O &&  A11 &&  !A10;

assign CIA1 = I_O && A11 && A10 && !A9 && !A8;
assign CIA2 = I_O && A11 && A10 && !A9 &&  A8;
assign IO1  = I_O && A11 && A10 &&  A9 && !A8;
assign IO2  = I_O && A11 && A10 &&  A9 &&  A8;

// "Created by JED2AHDL ABEL 4.10 on Wed Jul 19 15:37:23 1995
//
//TITLE
//'PLA chip in old version of Commodore 64'
//
//        c64pla device 'f100';
//
//"Device is a Signetics/Mullard/Phillips 82S100


//"Pin and Node Declarations
//          FE,  A13,  A14,  A15               PIN   1, 2, 3, 4;
//          _VA14,  _CHAREN,  _HIRAM,  _LORAM  PIN   5, 6, 7, 8;
//          _CAS,  ROMH,  ROML,  I_O           PIN   9,10,11,12;
//          GR_W,  GND,  CHAROM,  KERNAL       PIN  13,14,15,16;
//          BASIC,  CASRAM,  _OE,  VA12        PIN  17,18,19,20;
//          VA13,  _GAME,  _EXROM,  R__W       PIN  21,22,23,24;
//          _AEC,  BA,  A12,  VCC              PIN  25,26,27,28;
//
//        CASRAM ISTYPE 'Neg';
//        ROMH,ROML,I_O,GR_W,CHAROM,KERNAL,BASIC,CASRAM ISTYPE 'Com';
//        ROMH,ROML,I_O,GR_W,CHAROM,KERNAL,BASIC,CASRAM ISTYPE 'Invert';
//        X,K,Z,C,P,U,D = .X.,.K.,.Z.,.C.,.P.,.U.,.D.;
//EQUATIONS

wire Q7 = (_HIRAM && A15 && !A14 && A13 && !_AEC && R__W && !_EXROM && !_GAME
           || A15 && A14 && A13 && !_AEC && _EXROM && !_GAME
           || _AEC && _EXROM && !_GAME && VA13 && VA12 );

wire Q6 = (_LORAM && _HIRAM && A15 && !A14 && !A13 && !_AEC && R__W && !_EXROM
           || A15 && !A14 && !A13 && !_AEC && _EXROM && !_GAME );

wire Q5 = (_HIRAM && _CHAREN && A15 && A14 && !A13 && A12 && !_AEC && (BA || !R__W) && (!_EXROM || _GAME )
           || _LORAM && _CHAREN && A15 && A14 && !A13 && A12 && !_AEC && (BA || !R__W) && (!_EXROM || _GAME )
           || A15 && A14 && !A13 && A12 && !_AEC && (BA || !R__W ) && _EXROM && !_GAME );

wire Q3 = (_LORAM && !_CHAREN && A15 && A14 && !A13 && A12 && !_AEC && R__W && _GAME
           || _HIRAM && !_CHAREN && A15 && A14 && !A13 && A12 && !_AEC && R__W && (!_EXROM || _GAME )
           || _VA14 && _AEC && _GAME && !VA13 && VA12
           || _VA14 && _AEC && !_EXROM && !_GAME && !VA13 && VA12 );

wire Q2 = (_HIRAM && A15 && A14 && A13 && !_AEC && R__W && (!_EXROM || _GAME ) );

wire Q1 = (_LORAM && _HIRAM && A15 && !A14 && A13 && !_AEC && R__W && _GAME );

assign ROMH = Q7;
assign ROML = Q6;
assign I_O = Q5;
assign GR_W = (!_CAS && A15 && A14 && !A13 && A12 && !_AEC && !R__W );
assign CHAROM = Q3;
assign KERNAL = Q2;
assign BASIC = Q1;
assign CASRAM = !(_CAS || Q1 || Q2 || Q3 || Q5 || Q6 || Q7
                  || _EXROM && !_GAME && !A15 &&  A14
                  || _EXROM && !_GAME && !A15 && !A14 &&  A12
                  || _EXROM && !_GAME && !A15 && !A14 &&  A13
                  || _EXROM && !_GAME &&  A15 && !A14 &&  A13
                  || _EXROM && !_GAME &&  A15 &&  A14 && !A13 && !A12 );
endmodule

testbench/pla/tb_pla.v

`default_nettype none

module tb_pla;
reg clk;
reg rst_n;
reg[2:0] P;
reg[15:0] ADDR;
reg[14:0] VADDR;
reg AEC;
reg BA;
reg GAME_n;
reg EXTROM_n;
reg RW;


integer i;
integer j;

pla pla_e
(
    .A(ADDR),
    ._LORAM(P[0]),
    ._HIRAM(P[1]),
    ._CHAREN(P[2]),
    ._CAS(1'b0),
    .VA12(VADDR[12]),
    .VA13(VADDR[13]),
    ._VA14(!VADDR[14]),
    ._AEC(AEC),
    .BA(BA),
    ._GAME( GAME_n),
    ._EXROM( EXTROM_n),
    .R__W(!RW)
);

localparam CLK_PERIOD = 10;
always #(CLK_PERIOD/2) clk=~clk;


initial begin
    $dumpfile("tb_pla.vcd");
    $dumpvars(0, tb_pla);
end

initial begin
    P<=0;
    VADDR<=0;
    ADDR<=0;
    AEC <=0;
    BA<=0;
    GAME_n<=1;
    EXTROM_n<=1;
    RW<=0;
    

    #1 rst_n<=1'bx;clk<=1'bx;
    #(CLK_PERIOD*3) rst_n<=1;
    #(CLK_PERIOD*3) rst_n<=0;clk<=0;
    repeat(5) @(posedge clk);
    rst_n<=1;
    @(posedge clk);
    repeat(2) @(posedge clk);
    
    for(i=0; i < 7; i=i+1) begin
        P <= i;
        for(j=0; j < 16; j=j+1) begin
            ADDR <= j <<12;
            repeat(2) @(posedge clk);
        end
    end

    $finish(2);
end

endmodule
`default_nettype wire

sim/pla/tb_pla.vcd
$date
	Fri Dec 24 08:09:36 2021
$end
$version
	Icarus Verilog
$end
$timescale
	1s
$end
$scope module tb_pla $end
$var reg 16 ! ADDR [15:0] $end
$var reg 1 " AEC $end
$var reg 1 # BA $end
$var reg 1 $ EXTROM_n $end
$var reg 1 % GAME_n $end
$var reg 3 & P [2:0] $end
$var reg 1 ' RW $end
$var reg 15 ( VADDR [14:0] $end
$var reg 1 ) clk $end
$var reg 1 * rst_n $end
$var integer 32 + i [31:0] $end
$var integer 32 , j [31:0] $end
$scope module pla_e $end
$var wire 16 - A [15:0] $end
$var wire 1 # BA $end
$var wire 1 . BASIC $end
$var wire 1 / CHAROM $end
$var wire 1 0 CIA1 $end
$var wire 1 1 CIA2 $end
$var wire 1 2 COLOR_RAM $end
$var wire 1 3 GR_W $end
$var wire 1 4 IO1 $end
$var wire 1 5 IO2 $end
$var wire 1 6 I_O $end
$var wire 1 7 KERNAL $end
$var wire 1 8 Q1 $end
$var wire 1 9 Q2 $end
$var wire 1 : Q3 $end
$var wire 1 ; Q5 $end
$var wire 1 < Q6 $end
$var wire 1 = Q7 $end
$var wire 1 > ROMH $end
$var wire 1 ? ROML $end
$var wire 1 @ R__W $end
$var wire 1 A SID $end
$var wire 1 B VA12 $end
$var wire 1 C VA13 $end
$var wire 1 D VIC $end
$var wire 1 " _AEC $end
$var wire 1 E _CAS $end
$var wire 1 F _CHAREN $end
$var wire 1 $ _EXROM $end
$var wire 1 % _GAME $end
$var wire 1 G _HIRAM $end
$var wire 1 H _LORAM $end
$var wire 1 I _VA14 $end
$var wire 1 J CASRAM $end
$var wire 1 K A9 $end
$var wire 1 L A8 $end
$var wire 1 M A15 $end
$var wire 1 N A14 $end
$var wire 1 O A13 $end
$var wire 1 P A12 $end
$var wire 1 Q A11 $end
$var wire 1 R A10 $end
$upscope $end
$upscope $end
$enddefinitions $end
#0
$dumpvars
0R
0Q
0P
0O
0N
0M
0L
0K
1J
1I
0H
0G
0F
0E
0D
0C
0B
0A
1@
0?
0>
0=
0<
0;
0:
09
08
07
06
05
04
03
02
01
00
0/
0.
b0 -
bx ,
bx +
x*
x)
b0 (
0'
b0 &
1%
1$
0#
0"
b0 !
$end
#31
1*
#61
0)
0*
#65
1)
#70
0)
#75
1)
#80
0)
#85
1)
#90
0)
#95
1)
#100
0)
#105
1*
1)
#110
0)
#115
1)
#120
0)
#125
1)
#130
0)
#135
b0 ,
b0 +
1)
#140
0)
#145
1)
#150
0)
#155
1P
b1000000000000 !
b1000000000000 -
b1 ,
1)
#160
0)
#165
1)
#170
0)
#175
0P
1O
b10000000000000 !
b10000000000000 -
b10 ,
1)
#180
0)
#185
1)
#190
0)
#195
1P
b11000000000000 !
b11000000000000 -
b11 ,
1)
#200
0)
#205
1)
#210
0)
#215
0P
0O
1N
b100000000000000 !
b100000000000000 -
b100 ,
1)
#220
0)
#225
1)
#230
0)
#235
1P
b101000000000000 !
b101000000000000 -
b101 ,
1)
#240
0)
#245
1)
#250
0)
#255
0P
1O
b110000000000000 !
b110000000000000 -
b110 ,
1)
#260
0)
#265
1)
#270
0)
#275
1P
b111000000000000 !
b111000000000000 -
b111 ,
1)
#280
0)
#285
1)
#290
0)
#295
0P
0O
0N
1M
b1000000000000000 !
b1000000000000000 -
b1000 ,
1)
#300
0)
#305
1)
#310
0)
#315
1P
b1001000000000000 !
b1001000000000000 -
b1001 ,
1)
#320
0)
#325
1)
#330
0)
#335
0P
1O
b1010000000000000 !
b1010000000000000 -
b1010 ,
1)
#340
0)
#345
1)
#350
0)
#355
1P
b1011000000000000 !
b1011000000000000 -
b1011 ,
1)
#360
0)
#365
1)
#370
0)
#375
0P
0O
1N
b1100000000000000 !
b1100000000000000 -
b1100 ,
1)
#380
0)
#385
1)
#390
0)
#395
1P
b1101000000000000 !
b1101000000000000 -
b1101 ,
1)
#400
0)
#405
1)
#410
0)
#415
0P
1O
b1110000000000000 !
b1110000000000000 -
b1110 ,
1)
#420
0)
#425
1)
#430
0)
#435
1P
b1111000000000000 !
b1111000000000000 -
b1111 ,
1)
#440
0)
#445
1)
#450
0)
#455
0P
0O
0N
0M
1H
b0 !
b0 -
b1 &
b1 +
b0 ,
1)
#460
0)
#465
1)
#470
0)
#475
1P
b1000000000000 !
b1000000000000 -
b1 ,
1)
#480
0)
#485
1)
#490
0)
#495
0P
1O
b10000000000000 !
b10000000000000 -
b10 ,
1)
#500
0)
#505
1)
#510
0)
#515
1P
b11000000000000 !
b11000000000000 -
b11 ,
1)
#520
0)
#525
1)
#530
0)
#535
0P
0O
1N
b100000000000000 !
b100000000000000 -
b100 ,
1)
#540
0)
#545
1)
#550
0)
#555
1P
b101000000000000 !
b101000000000000 -
b101 ,
1)
#560
0)
#565
1)
#570
0)
#575
0P
1O
b110000000000000 !
b110000000000000 -
b110 ,
1)
#580
0)
#585
1)
#590
0)
#595
1P
b111000000000000 !
b111000000000000 -
b111 ,
1)
#600
0)
#605
1)
#610
0)
#615
0P
0O
0N
1M
b1000000000000000 !
b1000000000000000 -
b1000 ,
1)
#620
0)
#625
1)
#630
0)
#635
1P
b1001000000000000 !
b1001000000000000 -
b1001 ,
1)
#640
0)
#645
1)
#650
0)
#655
0P
1O
b1010000000000000 !
b1010000000000000 -
b1010 ,
1)
#660
0)
#665
1)
#670
0)
#675
1P
b1011000000000000 !
b1011000000000000 -
b1011 ,
1)
#680
0)
#685
1)
#690
0)
#695
0P
0O
1N
b1100000000000000 !
b1100000000000000 -
b1100 ,
1)
#700
0)
#705
1)
#710
0)
#715
0J
1/
1:
1P
b1101000000000000 !
b1101000000000000 -
b1101 ,
1)
#720
0)
#725
1)
#730
0)
#735
1J
0/
0:
0P
1O
b1110000000000000 !
b1110000000000000 -
b1110 ,
1)
#740
0)
#745
1)
#750
0)
#755
1P
b1111000000000000 !
b1111000000000000 -
b1111 ,
1)
#760
0)
#765
1)
#770
0)
#775
0P
0O
0N
0M
1G
0H
b0 !
b0 -
b10 &
b10 +
b0 ,
1)
#780
0)
#785
1)
#790
0)
#795
1P
b1000000000000 !
b1000000000000 -
b1 ,
1)
#800
0)
#805
1)
#810
0)
#815
0P
1O
b10000000000000 !
b10000000000000 -
b10 ,
1)
#820
0)
#825
1)
#830
0)
#835
1P
b11000000000000 !
b11000000000000 -
b11 ,
1)
#840
0)
#845
1)
#850
0)
#855
0P
0O
1N
b100000000000000 !
b100000000000000 -
b100 ,
1)
#860
0)
#865
1)
#870
0)
#875
1P
b101000000000000 !
b101000000000000 -
b101 ,
1)
#880
0)
#885
1)
#890
0)
#895
0P
1O
b110000000000000 !
b110000000000000 -
b110 ,
1)
#900
0)
#905
1)
#910
0)
#915
1P
b111000000000000 !
b111000000000000 -
b111 ,
1)
#920
0)
#925
1)
#930
0)
#935
0P
0O
0N
1M
b1000000000000000 !
b1000000000000000 -
b1000 ,
1)
#940
0)
#945
1)
#950
0)
#955
1P
b1001000000000000 !
b1001000000000000 -
b1001 ,
1)
#960
0)
#965
1)
#970
0)
#975
0P
1O
b1010000000000000 !
b1010000000000000 -
b1010 ,
1)
#980
0)
#985
1)
#990
0)
#995
1P
b1011000000000000 !
b1011000000000000 -
b1011 ,
1)
#1000
0)
#1005
1)
#1010
0)
#1015
0P
0O
1N
b1100000000000000 !
b1100000000000000 -
b1100 ,
1)
#1020
0)
#1025
1)
#1030
0)
#1035
0J
1/
1:
1P
b1101000000000000 !
b1101000000000000 -
b1101 ,
1)
#1040
0)
#1045
1)
#1050
0)
#1055
0/
0:
17
19
0P
1O
b1110000000000000 !
b1110000000000000 -
b1110 ,
1)
#1060
0)
#1065
1)
#1070
0)
#1075
1P
b1111000000000000 !
b1111000000000000 -
b1111 ,
1)
#1080
0)
#1085
1)
#1090
0)
#1095
1J
07
09
0P
0O
0N
0M
1H
b0 !
b0 -
b11 &
b11 +
b0 ,
1)
#1100
0)
#1105
1)
#1110
0)
#1115
1P
b1000000000000 !
b1000000000000 -
b1 ,
1)
#1120
0)
#1125
1)
#1130
0)
#1135
0P
1O
b10000000000000 !
b10000000000000 -
b10 ,
1)
#1140
0)
#1145
1)
#1150
0)
#1155
1P
b11000000000000 !
b11000000000000 -
b11 ,
1)
#1160
0)
#1165
1)
#1170
0)
#1175
0P
0O
1N
b100000000000000 !
b100000000000000 -
b100 ,
1)
#1180
0)
#1185
1)
#1190
0)
#1195
1P
b101000000000000 !
b101000000000000 -
b101 ,
1)
#1200
0)
#1205
1)
#1210
0)
#1215
0P
1O
b110000000000000 !
b110000000000000 -
b110 ,
1)
#1220
0)
#1225
1)
#1230
0)
#1235
1P
b111000000000000 !
b111000000000000 -
b111 ,
1)
#1240
0)
#1245
1)
#1250
0)
#1255
0P
0O
0N
1M
b1000000000000000 !
b1000000000000000 -
b1000 ,
1)
#1260
0)
#1265
1)
#1270
0)
#1275
1P
b1001000000000000 !
b1001000000000000 -
b1001 ,
1)
#1280
0)
#1285
1)
#1290
0)
#1295
0J
1.
18
0P
1O
b1010000000000000 !
b1010000000000000 -
b1010 ,
1)
#1300
0)
#1305
1)
#1310
0)
#1315
1P
b1011000000000000 !
b1011000000000000 -
b1011 ,
1)
#1320
0)
#1325
1)
#1330
0)
#1335
1J
0.
08
0P
0O
1N
b1100000000000000 !
b1100000000000000 -
b1100 ,
1)
#1340
0)
#1345
1)
#1350
0)
#1355
0J
1/
1:
1P
b1101000000000000 !
b1101000000000000 -
b1101 ,
1)
#1360
0)
#1365
1)
#1370
0)
#1375
0/
0:
17
19
0P
1O
b1110000000000000 !
b1110000000000000 -
b1110 ,
1)
#1380
0)
#1385
1)
#1390
0)
#1395
1P
b1111000000000000 !
b1111000000000000 -
b1111 ,
1)
#1400
0)
#1405
1)
#1410
0)
#1415
1J
07
09
0P
0O
0N
0M
1F
0G
0H
b0 !
b0 -
b100 &
b100 +
b0 ,
1)
#1420
0)
#1425
1)
#1430
0)
#1435
1P
b1000000000000 !
b1000000000000 -
b1 ,
1)
#1440
0)
#1445
1)
#1450
0)
#1455
0P
1O
b10000000000000 !
b10000000000000 -
b10 ,
1)
#1460
0)
#1465
1)
#1470
0)
#1475
1P
b11000000000000 !
b11000000000000 -
b11 ,
1)
#1480
0)
#1485
1)
#1490
0)
#1495
0P
0O
1N
b100000000000000 !
b100000000000000 -
b100 ,
1)
#1500
0)
#1505
1)
#1510
0)
#1515
1P
b101000000000000 !
b101000000000000 -
b101 ,
1)
#1520
0)
#1525
1)
#1530
0)
#1535
0P
1O
b110000000000000 !
b110000000000000 -
b110 ,
1)
#1540
0)
#1545
1)
#1550
0)
#1555
1P
b111000000000000 !
b111000000000000 -
b111 ,
1)
#1560
0)
#1565
1)
#1570
0)
#1575
0P
0O
0N
1M
b1000000000000000 !
b1000000000000000 -
b1000 ,
1)
#1580
0)
#1585
1)
#1590
0)
#1595
1P
b1001000000000000 !
b1001000000000000 -
b1001 ,
1)
#1600
0)
#1605
1)
#1610
0)
#1615
0P
1O
b1010000000000000 !
b1010000000000000 -
b1010 ,
1)
#1620
0)
#1625
1)
#1630
0)
#1635
1P
b1011000000000000 !
b1011000000000000 -
b1011 ,
1)
#1640
0)
#1645
1)
#1650
0)
#1655
0P
0O
1N
b1100000000000000 !
b1100000000000000 -
b1100 ,
1)
#1660
0)
#1665
1)
#1670
0)
#1675
1P
b1101000000000000 !
b1101000000000000 -
b1101 ,
1)
#1680
0)
#1685
1)
#1690
0)
#1695
0P
1O
b1110000000000000 !
b1110000000000000 -
b1110 ,
1)
#1700
0)
#1705
1)
#1710
0)
#1715
1P
b1111000000000000 !
b1111000000000000 -
b1111 ,
1)
#1720
0)
#1725
1)
#1730
0)
#1735
0P
0O
0N
0M
1H
b0 !
b0 -
b101 &
b101 +
b0 ,
1)
#1740
0)
#1745
1)
#1750
0)
#1755
1P
b1000000000000 !
b1000000000000 -
b1 ,
1)
#1760
0)
#1765
1)
#1770
0)
#1775
0P
1O
b10000000000000 !
b10000000000000 -
b10 ,
1)
#1780
0)
#1785
1)
#1790
0)
#1795
1P
b11000000000000 !
b11000000000000 -
b11 ,
1)
#1800
0)
#1805
1)
#1810
0)
#1815
0P
0O
1N
b100000000000000 !
b100000000000000 -
b100 ,
1)
#1820
0)
#1825
1)
#1830
0)
#1835
1P
b101000000000000 !
b101000000000000 -
b101 ,
1)
#1840
0)
#1845
1)
#1850
0)
#1855
0P
1O
b110000000000000 !
b110000000000000 -
b110 ,
1)
#1860
0)
#1865
1)
#1870
0)
#1875
1P
b111000000000000 !
b111000000000000 -
b111 ,
1)
#1880
0)
#1885
1)
#1890
0)
#1895
0P
0O
0N
1M
b1000000000000000 !
b1000000000000000 -
b1000 ,
1)
#1900
0)
#1905
1)
#1910
0)
#1915
1P
b1001000000000000 !
b1001000000000000 -
b1001 ,
1)
#1920
0)
#1925
1)
#1930
0)
#1935
0P
1O
b1010000000000000 !
b1010000000000000 -
b1010 ,
1)
#1940
0)
#1945
1)
#1950
0)
#1955
1P
b1011000000000000 !
b1011000000000000 -
b1011 ,
1)
#1960
0)
#1965
1)
#1970
0)
#1975
0P
0O
1N
b1100000000000000 !
b1100000000000000 -
b1100 ,
1)
#1980
0)
#1985
1)
#1990
0)
#1995
1P
b1101000000000000 !
b1101000000000000 -
b1101 ,
1)
#2000
0)
#2005
1)
#2010
0)
#2015
0P
1O
b1110000000000000 !
b1110000000000000 -
b1110 ,
1)
#2020
0)
#2025
1)
#2030
0)
#2035
1P
b1111000000000000 !
b1111000000000000 -
b1111 ,
1)
#2040
0)
#2045
1)
#2050
0)
#2055
0P
0O
0N
0M
1G
0H
b0 !
b0 -
b110 &
b110 +
b0 ,
1)
#2060
0)
#2065
1)
#2070
0)
#2075
1P
b1000000000000 !
b1000000000000 -
b1 ,
1)
#2080
0)
#2085
1)
#2090
0)
#2095
0P
1O
b10000000000000 !
b10000000000000 -
b10 ,
1)
#2100
0)
#2105
1)
#2110
0)
#2115
1P
b11000000000000 !
b11000000000000 -
b11 ,
1)
#2120
0)
#2125
1)
#2130
0)
#2135
0P
0O
1N
b100000000000000 !
b100000000000000 -
b100 ,
1)
#2140
0)
#2145
1)
#2150
0)
#2155
1P
b101000000000000 !
b101000000000000 -
b101 ,
1)
#2160
0)
#2165
1)
#2170
0)
#2175
0P
1O
b110000000000000 !
b110000000000000 -
b110 ,
1)
#2180
0)
#2185
1)
#2190
0)
#2195
1P
b111000000000000 !
b111000000000000 -
b111 ,
1)
#2200
0)
#2205
1)
#2210
0)
#2215
0P
0O
0N
1M
b1000000000000000 !
b1000000000000000 -
b1000 ,
1)
#2220
0)
#2225
1)
#2230
0)
#2235
1P
b1001000000000000 !
b1001000000000000 -
b1001 ,
1)
#2240
0)
#2245
1)
#2250
0)
#2255
0P
1O
b1010000000000000 !
b1010000000000000 -
b1010 ,
1)
#2260
0)
#2265
1)
#2270
0)
#2275
1P
b1011000000000000 !
b1011000000000000 -
b1011 ,
1)
#2280
0)
#2285
1)
#2290
0)
#2295
0P
0O
1N
b1100000000000000 !
b1100000000000000 -
b1100 ,
1)
#2300
0)
#2305
1)
#2310
0)
#2315
1P
b1101000000000000 !
b1101000000000000 -
b1101 ,
1)
#2320
0)
#2325
1)
#2330
0)
#2335
0J
17
19
0P
1O
b1110000000000000 !
b1110000000000000 -
b1110 ,
1)
#2340
0)
#2345
1)
#2350
0)
#2355
1P
b1111000000000000 !
b1111000000000000 -
b1111 ,
1)
#2360
0)
#2365
1)
#2370
0)
#2375
b111 +
b10000 ,
1)
